[{"id":"finding-znXEBtQk","date":"2018-07-16T00:10:04.248Z","mediaFilename":"finding-znXEBtQk.png","caption":"Ivysaur + <a href=\"http://digitalcollections.nypl.org/items/872d9d00-c643-012f-8b37-58d385a7bc34\">Cattleya victoria regina.</a>","altText":"Ivysaur @ Cattleya victoria regina.! http://digitalcollections.nypl.org/items/872d9d00-c643-012f-8b37-58d385a7bc34","postedToGit":true,"htmlFragment":"<li class=\"pane\">\n  <div class=\"time-stamp entry-meta\">\n    <a href=\"finding-znXEBtQk.html\">\n      <time datetime=\"2018-07-16T00:10:04.248Z\">2018-7-15 20:10:04</time>\n    </a>\n  </div><img src=\"media/finding-znXEBtQk.png\" alt=\"Ivysaur @ Cattleya victoria regina.! http://digitalcollections.nypl.org/items/872d9d00-c643-012f-8b37-58d385a7bc34\"></video><div class=\"media-caption entry-meta\">Ivysaur + <a href=\"http://digitalcollections.nypl.org/items/872d9d00-c643-012f-8b37-58d385a7bc34\">Cattleya victoria regina.</a></div></li>","postedSingleVideoPage":true},{"id":"finding-QbzGRwRD","date":"2018-07-16T06:49:04.455Z","mediaFilename":"finding-QbzGRwRD.png","caption":"Treecko – <a href=\"http://digitalcollections.nypl.org/items/2ac6d7f0-c633-012f-3c4e-58d385a7bc34\">Zoologie. Polypes. Cellaires.</a>","altText":"Treecko + Zoologie. Polypes. Cellaires.. http://digitalcollections.nypl.org/items/2ac6d7f0-c633-012f-3c4e-58d385a7bc34","postedToGit":true,"htmlFragment":"<li class=\"pane\">\n  <div class=\"time-stamp entry-meta\">\n    <a href=\"finding-QbzGRwRD.html\">\n      <time datetime=\"2018-07-16T06:49:04.455Z\">2018-7-16 02:49:04</time>\n    </a>\n  </div><img src=\"media/finding-QbzGRwRD.png\" alt=\"Treecko + Zoologie. Polypes. Cellaires.. http://digitalcollections.nypl.org/items/2ac6d7f0-c633-012f-3c4e-58d385a7bc34\"></video><div class=\"media-caption entry-meta\">Treecko – <a href=\"http://digitalcollections.nypl.org/items/2ac6d7f0-c633-012f-3c4e-58d385a7bc34\">Zoologie. Polypes. Cellaires.</a></div></li>","postedSingleVideoPage":true},{"id":"finding-GFMDkhpe","date":"2018-07-16T08:10:03.572Z","mediaFilename":"finding-GFMDkhpe.png","caption":" | <a href=\"http://digitalcollections.nypl.org/items/6a5ab6d0-c53e-012f-796f-58d385a7bc34\">Germany, Hessen, 1749-1828.</a>","altText":" on Germany, Hessen, 1749-1828.! http://digitalcollections.nypl.org/items/6a5ab6d0-c53e-012f-796f-58d385a7bc34","postedToGit":true,"htmlFragment":"<li class=\"pane\">\n  <div class=\"time-stamp entry-meta\">\n    <a href=\"finding-GFMDkhpe.html\">\n      <time datetime=\"2018-07-16T08:10:03.572Z\">2018-7-16 04:10:03</time>\n    </a>\n  </div><img src=\"media/finding-GFMDkhpe.png\" alt=\" on Germany, Hessen, 1749-1828.! http://digitalcollections.nypl.org/items/6a5ab6d0-c53e-012f-796f-58d385a7bc34\"></video><div class=\"media-caption entry-meta\"> | <a href=\"http://digitalcollections.nypl.org/items/6a5ab6d0-c53e-012f-796f-58d385a7bc34\">Germany, Hessen, 1749-1828.</a></div></li>","postedSingleVideoPage":true}]