{"id":"finding-DQNdAThf","date":"2018-02-05T13:10:06.870Z","mediaFilename":"finding-DQNdAThf.png","caption":"Simipour | <a href=\"http://digitalcollections.nypl.org/items/252d1420-c600-012f-2607-58d385a7bc34\">Manhattan V. 7, Plate No. 76 [Map bounded by Lenox Ave., W. 122nd St., 5th Ave., W. 119th St.]</a>!","altText":"Simipour @ Manhattan V. 7, Plate No. 76 [Map bounded by Lenox Ave., W. 122nd St., 5th Ave., W. 119th St.] http://digitalcollections.nypl.org/items/252d1420-c600-012f-2607-58d385a7bc34"}