{"id":"finding-ZoHGwtsm","date":"2018-04-04T18:10:07.192Z","mediaFilename":"finding-ZoHGwtsm.png","caption":"Riolu | <a href=\"http://digitalcollections.nypl.org/items/ac561000-c5da-012f-9122-58d385a7bc34\">The home of a white family with children. The windows look directly into the parlor from the street. The house was once a store. New Jersey.</a>!","altText":"Riolu + The home of a white family with children. The windows look directly into the parlor from the street. Th… http://digitalcollections.nypl.org/items/ac561000-c5da-012f-9122-58d385a7bc34"}