{"id":"finding-uCgEXIKq","date":"2018-08-19T14:10:04.911Z","mediaFilename":"finding-uCgEXIKq.png","caption":" on <a href=\"http://digitalcollections.nypl.org/items/7d426900-14d2-0131-c92d-58d385a7b928\">Le duc de Vendôme (Mr Aumer) dans Les pages du duc de Vendôme, ballet pantomime en 1 acte (Académie Rle. de musique).</a>!","altText":" ; Le duc de Vendôme (Mr Aumer) dans Les pages du duc de Vendôme, ballet pantomime en 1 acte (Académie Rle. de … http://digitalcollections.nypl.org/items/7d426900-14d2-0131-c92d-58d385a7b928"}